deatf/__init__.py
deatf/auxiliary_functions.py
deatf/evolution.py
deatf/mutation.py
deatf/network.py
deatf-0.3.1.dist-info/LICENSE
deatf-0.3.1.dist-info/METADATA
deatf-0.3.1.dist-info/WHEEL
deatf-0.3.1.dist-info/top_level.txt
deatf-0.3.1.dist-info/RECORD
