Metadata-Version: 2.1
Name: deatf
Version: 0.3.1
Summary: Distributed Evolutionary Algorithms in TensorFlow (DEATF) is a framework where networks generated with TensorFlow are evolved via DEAP.
Home-page: https://github.com/IvanHCenalmor/deatf
Author: Ivan Hidalgo
Author-email: ivanhcenalmor@domain.com
License: LGPLv3
Keywords: NEUROEVOLUTION,DEAP,TENSORFLOW,GENETIC,ALGORITHMS
Platform: UNKNOWN
Classifier: Programming Language :: Python :: 3
Classifier: License :: OSI Approved :: GNU Lesser General Public License v3 (LGPLv3)
Classifier: Operating System :: OS Independent
Requires-Python: !=3.9.*',>=3.5
License-File: LICENSE
Requires-Dist: numpy
Requires-Dist: tensorflow
Requires-Dist: deap
Requires-Dist: tensorflow-datasets
Requires-Dist: scikit-learn
Requires-Dist: pandas
